ampur/__init__.py
ampur/adding new learners.py
ampur/prep the docs.py
ampur/removing.py
ampur/retention.py
ampur-0.1.0.dist-info/METADATA
ampur-0.1.0.dist-info/WHEEL
ampur-0.1.0.dist-info/RECORD
