Metadata-Version: 2.1
Name: ampur
Version: 0.1.0
Summary: This program profiles according to the standards set by BRL implemented by GDE
Author: Siphiwe Themba
Requires-Python: >=3.12,<4.0
Classifier: Programming Language :: Python :: 3
Classifier: Programming Language :: Python :: 3.12
Requires-Dist: openpyxl (>=3.1.5,<4.0.0)
Requires-Dist: pandas (>=2.2.2,<3.0.0)
